[
  {
    "inscription": "Main website",
    "thumbnail": "monitor",
    "link": "/",
    "width": "34",
    "height": "31",
    "showOnMobile": false
  },
  {
    "inscription": "Golos.io news and updates",
    "thumbnail": "newspaper",
    "link": "/@golosio",
    "width": "26",
    "height": "26",
    "showOnMobile": false
  },
  {
    "inscription": "Facebook",
    "thumbnail": "facebook",
    "link": "https://www.facebook.com/www.golos.io/\n",
    "width": "14",
    "height": "30",
    "showOnMobile": false
  },
  {
    "inscription": "github",
    "thumbnail": "github",
    "link": "https://github.com/GolosChain/tolstoy",
    "width": "32",
    "height": "31",
    "showOnMobile": false
  },
  {
    "inscription": "Official mirror website",
    "thumbnail": "mirror",
    "link": "https://golos.blog",
    "width": "30",
    "height": "30",
    "showOnMobile": false
  },
  {
    "inscription": "ENG support channel",
    "thumbnail": "support_eng",
    "link": "https://tlg.name/golos_eng",
    "width": "30",
    "height": "31",
    "showOnMobile": true
  },
  {
    "inscription": "Best of Golos.io",
    "thumbnail": "like",
    "link": "https://tlg.name/golos_best",
    "width": "28",
    "height": "28",
    "showOnMobile": false
  },
  {
    "inscription": "Vkontakte",
    "thumbnail": "vk",
    "link": "https://vk.com/goloschain",
    "width": "30",
    "height": "20",
    "showOnMobile": false
  },
  {
    "inscription": "Partnership, press and media enquiries",
    "thumbnail": "mail",
    "link": "mailto:pr@golos.io",
    "width": "28",
    "height": "19",
    "showOnMobile": true
  }
]
